{
    "code": "ok",
    "result": {
        "id": "5b55abc29e94502ae0a292fe",
        "name": "C\u00e2y Xanh C\u00f4ng Vi\u00ean",
        "places": null,
        "placeDetails": [],
        "location": {
            "lng": 108.224256,
            "lat": 16.079822
        },
        "scale": 1,
        "bearing": 0,
        "elevation": 0,
        "heightScale": 1,
        "camera": null,
        "model": {
            "id": "58eb3d14ba54b90870de2aa8",
            "name": "C\u00e2y Xanh C\u00f4ng Vi\u00ean",
            "objName": "58eb3d14ba54b90870de2aa8",
            "objUrl": "https://hcm01.vstorage.vngcloud.vn/v1/AUTH_4486f66f671c41bab0d3dea1904626d4/sdk/models/58eb3d14ba54b90870de2aa8",
            "color": null,
            "type": "Object",
            "coordinates": [
                {
                    "lng": 108.224395,
                    "lat": 16.079936
                },
                {
                    "lng": 108.224395,
                    "lat": 16.079693
                },
                {
                    "lng": 108.224138,
                    "lat": 16.079936
                },
                {
                    "lng": 108.224138,
                    "lat": 16.079693
                }
            ],
            "height": 1,
            "textureName": "d833dbd4294b4c3fabdcf0ec6ee524cf.png",
            "textureUrl": "https://hcm01.vstorage.vngcloud.vn/v1/AUTH_4486f66f671c41bab0d3dea1904626d4/sdk/textures/d833dbd4294b4c3fabdcf0ec6ee524cf.png"
        },
        "types": null,
        "minZoom": null,
        "maxZoom": null,
        "addressComponents": [
            {
                "types": [
                    "street"
                ],
                "name": "B\u1ea1ch \u0110\u1eb1ng"
            },
            {
                "types": [
                    "admin_level_4"
                ],
                "name": "Ph\u01b0\u1eddng Th\u1ea1ch Thang"
            },
            {
                "types": [
                    "admin_level_3"
                ],
                "name": "Qu\u1eadn H\u1ea3i Ch\u00e2u"
            },
            {
                "types": [
                    "city",
                    "admin_level_2"
                ],
                "name": "Th\u00e0nh ph\u1ed1 \u0110\u00e0 N\u1eb5ng"
            },
            {
                "types": [
                    "admin_level_1"
                ],
                "name": "Vi\u1ec7t Nam"
            }
        ],
        "startDate": 975060000000,
        "endDate": 4099629600000,
        "source": null,
        "typeInfos": null,
        "metadata": null,
        "address": "B\u1ea1ch \u0110\u1eb1ng, Ph\u01b0\u1eddng Th\u1ea1ch Thang, Qu\u1eadn H\u1ea3i Ch\u00e2u, Th\u00e0nh ph\u1ed1 \u0110\u00e0 N\u1eb5ng, Vi\u1ec7t Nam"
    }
}