{
    "code": "ok",
    "result": {
        "id": "5d6e3f686589c60e5c573828",
        "name": "\u0110\u1eb7c S\u1ea3n \u00d4ng Ho\u00e0ng B\u00fan \u0110\u1eadu",
        "places": null,
        "placeDetails": [],
        "location": {
            "lng": 108.229807307014,
            "lat": 16.0662650650428
        },
        "scale": 1,
        "bearing": -75,
        "elevation": 0,
        "heightScale": 1,
        "camera": {
            "zoom": 22,
            "bearing": -76.10589758386548,
            "tilt": 79.52628939014939,
            "target": null
        },
        "model": {
            "id": null,
            "name": null,
            "objName": "5d6e3f686589c60e5c573826.jpg",
            "objUrl": "https://hcm01.vstorage.vngcloud.vn/v1/AUTH_4486f66f671c41bab0d3dea1904626d4/sdk/models/5d6e3f686589c60e5c573826.jpg",
            "color": null,
            "type": "Object",
            "coordinates": null,
            "height": 1,
            "textureName": "5d6e3f676589c60e5c573824.jpg",
            "textureUrl": "https://hcm01.vstorage.vngcloud.vn/v1/AUTH_4486f66f671c41bab0d3dea1904626d4/sdk/textures/5d6e3f676589c60e5c573824.jpg"
        },
        "types": [
            "restaurant"
        ],
        "minZoom": 17,
        "maxZoom": 19,
        "addressComponents": [
            {
                "types": [
                    "street"
                ],
                "name": "Tr\u1ea7n H\u01b0ng \u0110\u1ea1o"
            },
            {
                "types": [
                    "admin_level_4"
                ],
                "name": "Ph\u01b0\u1eddng An H\u1ea3i T\u00e2y"
            },
            {
                "types": [
                    "admin_level_3"
                ],
                "name": "Qu\u1eadn S\u01a1n Tr\u00e0"
            },
            {
                "types": [
                    "city",
                    "admin_level_2"
                ],
                "name": "Th\u00e0nh ph\u1ed1 \u0110\u00e0 N\u1eb5ng"
            },
            {
                "types": [
                    "admin_level_1"
                ],
                "name": "Vi\u1ec7t Nam"
            }
        ],
        "startDate": null,
        "endDate": null,
        "source": null,
        "typeInfos": {
            "restaurant": "Nh\u00e0 h\u00e0ng"
        },
        "metadata": null,
        "address": "Tr\u1ea7n H\u01b0ng \u0110\u1ea1o, Ph\u01b0\u1eddng An H\u1ea3i T\u00e2y, Qu\u1eadn S\u01a1n Tr\u00e0, Th\u00e0nh ph\u1ed1 \u0110\u00e0 N\u1eb5ng, Vi\u1ec7t Nam"
    }
}