{
    "code": "ok",
    "result": {
        "id": "60b5f3de10b9793609aab140",
        "name": "S\u1edf C\u1ea3nh S\u00e1t PCCC H\u00e0 N\u1ed9i",
        "places": null,
        "placeDetails": [],
        "location": {
            "lng": 105.85620095109778,
            "lat": 21.020522680303785
        },
        "scale": 1,
        "bearing": -108,
        "elevation": 0,
        "heightScale": 1,
        "camera": {
            "zoom": 19,
            "bearing": 120.12199353449611,
            "tilt": 61.5,
            "target": {
                "lng": 105.85676273266728,
                "lat": 21.020929044506133
            }
        },
        "model": {
            "id": null,
            "name": null,
            "objName": "60b5f3cd10b9793609aab13c.obj",
            "objUrl": "https://hcm01.vstorage.vngcloud.vn/v1/AUTH_4486f66f671c41bab0d3dea1904626d4/sdk/models/60b5f3cd10b9793609aab13c.obj",
            "color": null,
            "type": "Object",
            "coordinates": [
                {
                    "lng": 105.8563002486148,
                    "lat": 21.020521914714678
                },
                {
                    "lng": 105.85630024858582,
                    "lat": 21.020432083186265
                },
                {
                    "lng": 105.85620401281419,
                    "lat": 21.020432083186265
                },
                {
                    "lng": 105.8562040127852,
                    "lat": 21.020521914714678
                },
                {
                    "lng": 105.8563002486148,
                    "lat": 21.020521914714678
                }
            ],
            "height": 1,
            "textureName": "60b5f3cf10b9793609aab13e.jpg",
            "textureUrl": "https://hcm01.vstorage.vngcloud.vn/v1/AUTH_4486f66f671c41bab0d3dea1904626d4/sdk/textures/60b5f3cf10b9793609aab13e.jpg"
        },
        "types": [],
        "minZoom": 17,
        "maxZoom": 19,
        "addressComponents": [
            {
                "types": [
                    "admin_level_2"
                ],
                "name": "Th\u00e0nh ph\u1ed1 H\u00e0 N\u1ed9i"
            },
            {
                "types": [
                    "admin_level_3"
                ],
                "name": "Qu\u1eadn Ho\u00e0n Ki\u1ebfm"
            },
            {
                "types": [
                    "admin_level_4"
                ],
                "name": "Ph\u01b0\u1eddng Phan Chu Trinh"
            },
            {
                "types": [
                    "street"
                ],
                "name": "Phan Chu Trinh"
            }
        ],
        "startDate": null,
        "endDate": null,
        "source": {
            "name": "vmp"
        },
        "typeInfos": {},
        "metadata": null,
        "address": "Phan Chu Trinh, Ph\u01b0\u1eddng Phan Chu Trinh, Qu\u1eadn Ho\u00e0n Ki\u1ebfm, Th\u00e0nh ph\u1ed1 H\u00e0 N\u1ed9i"
    }
}